tests/input/stim.svh
// H11e (finding F-L7, D-029): the stimulus generator of the fixture testbenches.
// A simulator's $urandom sequence changes between versions (Verilator 5.031 -> 5.052), so the
// committed traces could not be reproduced. This xorshift32 generator (Marsaglia, 2003) is plain
// SystemVerilog: the same seed gives the same sequence on every simulator and version.
// Included inside the testbench module: `include "stim.svh"
int unsigned stim_state = 32'd1;

function automatic void stim_seed(int unsigned s);
  stim_state = (s == 0) ? 32'd1 : s; // xorshift must not start from 0
endfunction

function automatic int unsigned stim_next();
  stim_state ^= stim_state << 13;
  stim_state ^= stim_state >> 17;
  stim_state ^= stim_state << 5;
  return stim_state;
endfunction

tests/input/coi/counter/rtl/counter.sv
// mod-10 counter with enable: register feedback, combinational wrap
module counter (
    input  logic       clk,
    input  logic       rst,
    input  logic       en,
    output logic [3:0] cnt,
    output logic       wrap
);
  assign wrap = en && (cnt == 4'd9);
  always_ff @(posedge clk)
    if (rst) cnt <= 4'd0;
    else if (en) cnt <= (cnt == 4'd9) ? 4'd0 : cnt + 4'd1;
endmodule

tests/input/coi/counter/tb.sv
// testbench for the H4 COI fixture 'counter': seeded random stimulus on the falling edge
`ifndef VCD
`define VCD "trace.vcd"
`endif
module tb;
  `include "stim.svh"   // the stimulus generator (H11e, D-029)
  logic clk = 1'b0;
  logic rst;
  logic en;
  logic [3:0] cnt;
  logic wrap;
  counter dut (.*);
  always #5 clk = ~clk;
`ifdef PERTURB
  `include "perturb.svh"
`endif
  initial begin
    string vcd;
    int unsigned seed;
    if (!$value$plusargs("vcd=%s", vcd)) vcd = `VCD;
    $dumpfile(vcd);
    $dumpvars(0, tb);
    if (!$value$plusargs("seed=%d", seed)) seed = 1;
    stim_seed(seed);
    rst = '0; en = '0;
    rst = 1'b1;
    repeat (2) @(negedge clk);
    rst = 1'b0;
    repeat (200) begin
      @(negedge clk);
      rst = (stim_next() % 40) == 0; en = (stim_next() % 4) != 0;
    end
    $finish;
  end
endmodule

tests/input/coi/counter/trace.vcd
$version Generated by VerilatedVcd $end
$timescale 1ps $end
 $scope module $rootio $end
 $upscope $end
 $scope module tb $end
  $var wire 1 # clk $end
  $var wire 1 $ rst $end
  $var wire 1 % en $end
  $var wire 4 & cnt [3:0] $end
  $var wire 1 ' wrap $end
  $scope module dut $end
   $var wire 1 # clk $end
   $var wire 1 $ rst $end
   $var wire 1 % en $end
   $var wire 4 & cnt [3:0] $end
   $var wire 1 ' wrap $end
  $upscope $end
  $scope module unnamedblk1 $end
   $var wire 32 ( seed [31:0] $end
  $upscope $end
 $upscope $end
$enddefinitions $end


#0
0#
1$
0%
b0000 &
0'
b00000000000000000000000000000001 (
#5
1#
#10
0#
#15
1#
#20
0#
0$
#25
1#
#30
0#
1%
#35
1#
b0001 &
#40
0#
#45
1#
b0010 &
#50
0#
0%
#55
1#
#60
0#
#65
1#
#70
0#
1%
#75
1#
b0011 &
#80
0#
0%
#85
1#
#90
0#
1%
#95
1#
b0100 &
#100
0#
#105
1#
b0101 &
#110
0#
#115
1#
b0110 &
#120
0#
#125
1#
b0111 &
#130
0#
#135
1#
b1000 &
#140
0#
#145
1#
b1001 &
1'
#150
0#
0%
0'
#155
1#
#160
0#
1%
1'
#165
1#
b0000 &
0'
#170
0#
#175
1#
b0001 &
#180
0#
0%
#185
1#
#190
0#
#195
1#
#200
0#
1%
#205
1#
b0010 &
#210
0#
#215
1#
b0011 &
#220
0#
#225
1#
b0100 &
#230
0#
#235
1#
b0101 &
#240
0#
#245
1#
b0110 &
#250
0#
#255
1#
b0111 &
#260
0#
#265
1#
b1000 &
#270
0#
0%
#275
1#
#280
0#
1%
#285
1#
b1001 &
1'
#290
0#
0%
0'
#295
1#
#300
0#
#305
1#
#310
0#
#315
1#
#320
0#
#325
1#
#330
0#
1%
1'
#335
1#
b0000 &
0'
#340
0#
#345
1#
b0001 &
#350
0#
#355
1#
b0010 &
#360
0#
0%
#365
1#
#370
0#
1%
#375
1#
b0011 &
#380
0#
#385
1#
b0100 &
#390
0#
#395
1#
b0101 &
#400
0#
#405
1#
b0110 &
#410
0#
0%
#415
1#
#420
0#
1%
#425
1#
b0111 &
#430
0#
0%
#435
1#
#440
0#
#445
1#
#450
0#
#455
1#
#460
0#
1%
#465
1#
b1000 &
#470
0#
#475
1#
b1001 &
1'
#480
0#
#485
1#
b0000 &
0'
#490
0#
#495
1#
b0001 &
#500
0#
0%
#505
1#
#510
0#
1%
#515
1#
b0010 &
#520
0#
0%
#525
1#
#530
0#
1%
#535
1#
b0011 &
#540
0#
#545
1#
b0100 &
#550
0#
#555
1#
b0101 &
#560
0#
#565
1#
b0110 &
#570
0#
0%
#575
1#
#580
0#
1%
#585
1#
b0111 &
#590
0#
#595
1#
b1000 &
#600
0#
0%
#605
1#
#610
0#
1%
#615
1#
b1001 &
1'
#620
0#
#625
1#
b0000 &
0'
#630
0#
#635
1#
b0001 &
#640
0#
#645
1#
b0010 &
#650
0#
0%
#655
1#
#660
0#
1%
#665
1#
b0011 &
#670
0#
#675
1#
b0100 &
#680
0#
#685
1#
b0101 &
#690
0#
#695
1#
b0110 &
#700
0#
#705
1#
b0111 &
#710
0#
#715
1#
b1000 &
#720
0#
0%
#725
1#
#730
0#
1%
#735
1#
b1001 &
1'
#740
0#
0%
0'
#745
1#
#750
0#
1%
1'
#755
1#
b0000 &
0'
#760
0#
0%
#765
1#
#770
0#
1%
#775
1#
b0001 &
#780
0#
#785
1#
b0010 &
#790
0#
#795
1#
b0011 &
#800
0#
#805
1#
b0100 &
#810
0#
#815
1#
b0101 &
#820
0#
#825
1#
b0110 &
#830
0#
#835
1#
b0111 &
#840
0#
0%
#845
1#
#850
0#
1%
#855
1#
b1000 &
#860
0#
#865
1#
b1001 &
1'
#870
0#
#875
1#
b0000 &
0'
#880
0#
#885
1#
b0001 &
#890
0#
0%
#895
1#
#900
0#
#905
1#
#910
0#
#915
1#
#920
0#
1%
#925
1#
b0010 &
#930
0#
0%
#935
1#
#940
0#
1%
#945
1#
b0011 &
#950
0#
#955
1#
b0100 &
#960
0#
#965
1#
b0101 &
#970
0#
#975
1#
b0110 &
#980
0#
0%
#985
1#
#990
0#
1%
#995
1#
b0111 &
#1000
0#
#1005
1#
b1000 &
#1010
0#
#1015
1#
b1001 &
1'
#1020
0#
#1025
1#
b0000 &
0'
#1030
0#
#1035
1#
b0001 &
#1040
0#
#1045
1#
b0010 &
#1050
0#
0%
#1055
1#
#1060
0#
1%
#1065
1#
b0011 &
#1070
0#
#1075
1#
b0100 &
#1080
0#
#1085
1#
b0101 &
#1090
0#
#1095
1#
b0110 &
#1100
0#
#1105
1#
b0111 &
#1110
0#
#1115
1#
b1000 &
#1120
0#
#1125
1#
b1001 &
1'
#1130
0#
0%
0'
#1135
1#
#1140
0#
1%
1'
#1145
1#
b0000 &
0'
#1150
0#
#1155
1#
b0001 &
#1160
0#
#1165
1#
b0010 &
#1170
0#
#1175
1#
b0011 &
#1180
0#
#1185
1#
b0100 &
#1190
0#
#1195
1#
b0101 &
#1200
0#
#1205
1#
b0110 &
#1210
0#
#1215
1#
b0111 &
#1220
0#
#1225
1#
b1000 &
#1230
0#
#1235
1#
b1001 &
1'
#1240
0#
#1245
1#
b0000 &
0'
#1250
0#
#1255
1#
b0001 &
#1260
0#
#1265
1#
b0010 &
#1270
0#
#1275
1#
b0011 &
#1280
0#
#1285
1#
b0100 &
#1290
0#
#1295
1#
b0101 &
#1300
0#
#1305
1#
b0110 &
#1310
0#
0%
#1315
1#
#1320
0#
#1325
1#
#1330
0#
1%
#1335
1#
b0111 &
#1340
0#
#1345
1#
b1000 &
#1350
0#
#1355
1#
b1001 &
1'
#1360
0#
#1365
1#
b0000 &
0'
#1370
0#
0%
#1375
1#
#1380
0#
1%
#1385
1#
b0001 &
#1390
0#
#1395
1#
b0010 &
#1400
0#
#1405
1#
b0011 &
#1410
0#
#1415
1#
b0100 &
#1420
0#
#1425
1#
b0101 &
#1430
0#
#1435
1#
b0110 &
#1440
0#
0%
#1445
1#
#1450
0#
#1455
1#
#1460
0#
1%
#1465
1#
b0111 &
#1470
0#
#1475
1#
b1000 &
#1480
0#
#1485
1#
b1001 &
1'
#1490
0#
0%
0'
#1495
1#
#1500
0#
1%
1'
#1505
1#
b0000 &
0'
#1510
0#
#1515
1#
b0001 &
#1520
0#
#1525
1#
b0010 &
#1530
0#
0%
#1535
1#
#1540
0#
1%
#1545
1#
b0011 &
#1550
0#
#1555
1#
b0100 &
#1560
0#
#1565
1#
b0101 &
#1570
0#
#1575
1#
b0110 &
#1580
0#
#1585
1#
b0111 &
#1590
0#
0%
#1595
1#
#1600
0#
1%
#1605
1#
b1000 &
#1610
0#
0%
#1615
1#
#1620
0#
1%
#1625
1#
b1001 &
1'
#1630
0#
#1635
1#
b0000 &
0'
#1640
0#
#1645
1#
b0001 &
#1650
0#
#1655
1#
b0010 &
#1660
0#
#1665
1#
b0011 &
#1670
0#
0%
#1675
1#
#1680
0#
#1685
1#
#1690
0#
1%
#1695
1#
b0100 &
#1700
0#
#1705
1#
b0101 &
#1710
0#
0%
#1715
1#
#1720
0#
1%
#1725
1#
b0110 &
#1730
0#
#1735
1#
b0111 &
#1740
0#
#1745
1#
b1000 &
#1750
0#
0%
#1755
1#
#1760
0#
1%
#1765
1#
b1001 &
1'
#1770
0#
#1775
1#
b0000 &
0'
#1780
0#
#1785
1#
b0001 &
#1790
0#
#1795
1#
b0010 &
#1800
0#
0%
#1805
1#
#1810
0#
1%
#1815
1#
b0011 &
#1820
0#
#1825
1#
b0100 &
#1830
0#
#1835
1#
b0101 &
#1840
0#
#1845
1#
b0110 &
#1850
0#
#1855
1#
b0111 &
#1860
0#
#1865
1#
b1000 &
#1870
0#
#1875
1#
b1001 &
1'
#1880
0#
#1885
1#
b0000 &
0'
#1890
0#
#1895
1#
b0001 &
#1900
0#
#1905
1#
b0010 &
#1910
0#
#1915
1#
b0011 &
#1920
0#
#1925
1#
b0100 &
#1930
0#
0%
#1935
1#
#1940
0#
1%
#1945
1#
b0101 &
#1950
0#
#1955
1#
b0110 &
#1960
0#
0%
#1965
1#
#1970
0#
#1975
1#
#1980
0#
1%
#1985
1#
b0111 &
#1990
0#
0%
#1995
1#
#2000
0#
1%
#2005
1#
b1000 &
#2010
0#
0%
#2015
1#
#2020
0#
1%
