tests/input/stim.svh
// H11e (finding F-L7, D-029): the stimulus generator of the fixture testbenches.
// A simulator's $urandom sequence changes between versions (Verilator 5.031 -> 5.052), so the
// committed traces could not be reproduced. This xorshift32 generator (Marsaglia, 2003) is plain
// SystemVerilog: the same seed gives the same sequence on every simulator and version.
// Included inside the testbench module: `include "stim.svh"
int unsigned stim_state = 32'd1;

function automatic void stim_seed(int unsigned s);
  stim_state = (s == 0) ? 32'd1 : s; // xorshift must not start from 0
endfunction

function automatic int unsigned stim_next();
  stim_state ^= stim_state << 13;
  stim_state ^= stim_state >> 17;
  stim_state ^= stim_state << 5;
  return stim_state;
endfunction

tests/input/coi/multipath/rtl/multipath.sv
// 'a' reaches y combinationally and through two registers; 'b' reaches only z
module multipath (
    input  logic clk,
    input  logic a,
    input  logic b,
    output logic y,
    output logic z
);
  logic r1, r2, rb;
  always_ff @(posedge clk) begin
    r1 <= a;
    r2 <= r1;
    rb <= b;
  end
  assign y = a ^ r2;
  assign z = rb;
endmodule

tests/input/coi/multipath/tb.sv
// testbench for the H4 COI fixture 'multipath': seeded random stimulus on the falling edge
`ifndef VCD
`define VCD "trace.vcd"
`endif
module tb;
  `include "stim.svh"   // the stimulus generator (H11e, D-029)
  logic clk = 1'b0;
  logic a;
  logic b;
  logic y;
  logic z;
  multipath dut (.*);
  always #5 clk = ~clk;
`ifdef PERTURB
  `include "perturb.svh"
`endif
  initial begin
    string vcd;
    int unsigned seed;
    if (!$value$plusargs("vcd=%s", vcd)) vcd = `VCD;
    $dumpfile(vcd);
    $dumpvars(0, tb);
    if (!$value$plusargs("seed=%d", seed)) seed = 1;
    stim_seed(seed);
    a = '0; b = '0;
    repeat (200) begin
      @(negedge clk);
      a = 1'(stim_next()); b = 1'(stim_next());
    end
    $finish;
  end
endmodule

tests/input/coi/multipath/trace.vcd
$version Generated by VerilatedVcd $end
$timescale 1ps $end
 $scope module $rootio $end
 $upscope $end
 $scope module tb $end
  $var wire 1 & clk $end
  $var wire 1 ' a $end
  $var wire 1 ( b $end
  $var wire 1 ) y $end
  $var wire 1 # z $end
  $scope module dut $end
   $var wire 1 & clk $end
   $var wire 1 ' a $end
   $var wire 1 ( b $end
   $var wire 1 ) y $end
   $var wire 1 # z $end
   $var wire 1 $ r1 $end
   $var wire 1 % r2 $end
   $var wire 1 # rb $end
  $upscope $end
  $scope module unnamedblk1 $end
   $var wire 32 * seed [31:0] $end
  $upscope $end
 $upscope $end
$enddefinitions $end


#0
0#
0$
0%
0&
0'
0(
0)
b00000000000000000000000000000001 *
#5
1&
#10
0&
1'
1(
1)
#15
1#
1$
1&
#20
0&
0(
#25
0#
1%
1&
0)
#30
0&
0'
1)
#35
0$
1&
#40
0&
1'
0)
#45
1$
0%
1&
1)
#50
0&
0'
0)
#55
0$
1%
1&
1)
#60
0&
1'
0)
#65
1$
0%
1&
1)
#70
0&
1(
#75
1#
1%
1&
0)
#80
0&
0'
1)
#85
0$
1&
#90
0&
1'
0)
#95
1$
0%
1&
1)
#100
0&
0'
0)
#105
0$
1%
1&
1)
#110
0&
#115
0%
1&
0)
#120
0&
1'
1)
#125
1$
1&
#130
0&
0(
#135
0#
1%
1&
0)
#140
0&
#145
1&
#150
0&
0'
1)
#155
0$
1&
#160
0&
1'
0)
#165
1$
0%
1&
1)
#170
0&
0'
0)
#175
0$
1%
1&
1)
#180
0&
1'
1(
0)
#185
1#
1$
0%
1&
1)
#190
0&
0'
0(
0)
#195
0#
0$
1%
1&
1)
#200
0&
1(
#205
1#
0%
1&
0)
#210
0&
#215
1&
#220
0&
#225
1&
#230
0&
#235
1&
#240
0&
1'
0(
1)
#245
0#
1$
1&
#250
0&
#255
1%
1&
0)
#260
0&
0'
1)
#265
0$
1&
#270
0&
1'
0)
#275
1$
0%
1&
1)
#280
0&
0'
0)
#285
0$
1%
1&
1)
#290
0&
1'
0)
#295
1$
0%
1&
1)
#300
0&
#305
1%
1&
0)
#310
0&
1(
#315
1#
1&
#320
0&
0'
0(
1)
#325
0#
0$
1&
#330
0&
#335
0%
1&
0)
#340
0&
1'
1)
#345
1$
1&
#350
0&
0'
1(
0)
#355
1#
0$
1%
1&
1)
#360
0&
#365
0%
1&
0)
#370
0&
1'
1)
#375
1$
1&
#380
0&
#385
1%
1&
0)
#390
0&
0(
#395
0#
1&
#400
0&
0'
1)
#405
0$
1&
#410
0&
1'
0)
#415
1$
0%
1&
1)
#420
0&
0'
0)
#425
0$
1%
1&
1)
#430
0&
#435
0%
1&
0)
#440
0&
1'
1(
1)
#445
1#
1$
1&
#450
0&
#455
1%
1&
0)
#460
0&
0'
1)
#465
0$
1&
#470
0&
1'
0)
#475
1$
0%
1&
1)
#480
0&
0'
0(
0)
#485
0#
0$
1%
1&
1)
#490
0&
#495
0%
1&
0)
#500
0&
#505
1&
#510
0&
#515
1&
#520
0&
1'
1)
#525
1$
1&
#530
0&
1(
#535
1#
1%
1&
0)
#540
0&
0'
1)
#545
0$
1&
#550
0&
0(
#555
0#
0%
1&
0)
#560
0&
1(
#565
1#
1&
#570
0&
#575
1&
#580
0&
1'
0(
1)
#585
0#
1$
1&
#590
0&
1(
#595
1#
1%
1&
0)
#600
0&
#605
1&
#610
0&
#615
1&
#620
0&
0'
1)
#625
0$
1&
#630
0&
0(
#635
0#
0%
1&
0)
#640
0&
1'
1(
1)
#645
1#
1$
1&
#650
0&
0'
0(
0)
#655
0#
0$
1%
1&
1)
#660
0&
1'
1(
0)
#665
1#
1$
0%
1&
1)
#670
0&
0'
0)
#675
0$
1%
1&
1)
#680
0&
1'
0)
#685
1$
0%
1&
1)
#690
0&
0'
0)
#695
0$
1%
1&
1)
#700
0&
0(
#705
0#
0%
1&
0)
#710
0&
1(
#715
1#
1&
#720
0&
0(
#725
0#
1&
#730
0&
1(
#735
1#
1&
#740
0&
0(
#745
0#
1&
#750
0&
1(
#755
1#
1&
#760
0&
1'
0(
1)
#765
0#
1$
1&
#770
0&
#775
1%
1&
0)
#780
0&
0'
1)
#785
0$
1&
#790
0&
1(
#795
1#
0%
1&
0)
#800
0&
1'
1)
#805
1$
1&
#810
0&
#815
1%
1&
0)
#820
0&
0'
0(
1)
#825
0#
0$
1&
#830
0&
1'
1(
0)
#835
1#
1$
0%
1&
1)
#840
0&
0(
#845
0#
1%
1&
0)
#850
0&
0'
1(
1)
#855
1#
0$
1&
#860
0&
#865
0%
1&
0)
#870
0&
1'
0(
1)
#875
0#
1$
1&
#880
0&
#885
1%
1&
0)
#890
0&
#895
1&
#900
0&
#905
1&
#910
0&
0'
1)
#915
0$
1&
#920
0&
1'
1(
0)
#925
1#
1$
0%
1&
1)
#930
0&
0'
0)
#935
0$
1%
1&
1)
#940
0&
0(
#945
0#
0%
1&
0)
#950
0&
1(
#955
1#
1&
#960
0&
1'
0(
1)
#965
0#
1$
1&
#970
0&
0'
1(
0)
#975
1#
0$
1%
1&
1)
#980
0&
1'
0(
0)
#985
0#
1$
0%
1&
1)
#990
0&
0'
1(
0)
#995
1#
0$
1%
1&
1)
#1000
0&
#1005
0%
1&
0)
#1010
0&
#1015
1&
#1020
0&
#1025
1&
#1030
0&
1'
0(
1)
#1035
0#
1$
1&
#1040
0&
0'
1(
0)
#1045
1#
0$
1%
1&
1)
#1050
0&
0(
#1055
0#
0%
1&
0)
#1060
0&
#1065
1&
#1070
0&
1'
1)
#1075
1$
1&
#1080
0&
1(
#1085
1#
1%
1&
0)
#1090
0&
0'
1)
#1095
0$
1&
#1100
0&
1'
0)
#1105
1$
0%
1&
1)
#1110
0&
0(
#1115
0#
1%
1&
0)
#1120
0&
0'
1)
#1125
0$
1&
#1130
0&
1(
#1135
1#
0%
1&
0)
#1140
0&
#1145
1&
#1150
0&
1'
1)
#1155
1$
1&
#1160
0&
#1165
1%
1&
0)
#1170
0&
0'
1)
#1175
0$
1&
#1180
0&
#1185
0%
1&
0)
#1190
0&
1'
1)
#1195
1$
1&
#1200
0&
#1205
1%
1&
0)
#1210
0&
#1215
1&
#1220
0&
#1225
1&
#1230
0&
#1235
1&
#1240
0&
0'
1)
#1245
0$
1&
#1250
0&
1'
0(
0)
#1255
0#
1$
0%
1&
1)
#1260
0&
0'
0)
#1265
0$
1%
1&
1)
#1270
0&
#1275
0%
1&
0)
#1280
0&
1'
1(
1)
#1285
1#
1$
1&
#1290
0&
0'
0(
0)
#1295
0#
0$
1%
1&
1)
#1300
0&
1'
0)
#1305
1$
0%
1&
1)
#1310
0&
0'
1(
0)
#1315
1#
0$
1%
1&
1)
#1320
0&
#1325
0%
1&
0)
#1330
0&
1'
1)
#1335
1$
1&
#1340
0&
#1345
1%
1&
0)
#1350
0&
0(
#1355
0#
1&
#1360
0&
1(
#1365
1#
1&
#1370
0&
0'
1)
#1375
0$
1&
#1380
0&
1'
0(
0)
#1385
0#
1$
0%
1&
1)
#1390
0&
0'
1(
0)
#1395
1#
0$
1%
1&
1)
#1400
0&
#1405
0%
1&
0)
#1410
0&
1'
1)
#1415
1$
1&
#1420
0&
0(
#1425
0#
1%
1&
0)
#1430
0&
0'
1)
#1435
0$
1&
#1440
0&
#1445
0%
1&
0)
#1450
0&
1(
#1455
1#
1&
#1460
0&
0(
#1465
0#
1&
#1470
0&
#1475
1&
#1480
0&
1'
1(
1)
#1485
1#
1$
1&
#1490
0&
0'
0)
#1495
0$
1%
1&
1)
#1500
0&
1'
0)
#1505
1$
0%
1&
1)
#1510
0&
0'
0(
0)
#1515
0#
0$
1%
1&
1)
#1520
0&
1(
#1525
1#
0%
1&
0)
#1530
0&
#1535
1&
#1540
0&
1'
0(
1)
#1545
0#
1$
1&
#1550
0&
0'
0)
#1555
0$
1%
1&
1)
#1560
0&
1'
1(
0)
#1565
1#
1$
0%
1&
1)
#1570
0&
0(
#1575
0#
1%
1&
0)
#1580
0&
1(
#1585
1#
1&
#1590
0&
0(
#1595
0#
1&
#1600
0&
1(
#1605
1#
1&
#1610
0&
#1615
1&
#1620
0&
#1625
1&
#1630
0&
0'
1)
#1635
0$
1&
#1640
0&
#1645
0%
1&
0)
#1650
0&
1'
0(
1)
#1655
0#
1$
1&
#1660
0&
0'
0)
#1665
0$
1%
1&
1)
#1670
0&
1'
0)
#1675
1$
0%
1&
1)
#1680
0&
0'
1(
0)
#1685
1#
0$
1%
1&
1)
#1690
0&
1'
0(
0)
#1695
0#
1$
0%
1&
1)
#1700
0&
1(
#1705
1#
1%
1&
0)
#1710
0&
0'
0(
1)
#1715
0#
0$
1&
#1720
0&
1'
0)
#1725
1$
0%
1&
1)
#1730
0&
0'
0)
#1735
0$
1%
1&
1)
#1740
0&
1(
#1745
1#
0%
1&
0)
#1750
0&
1'
1)
#1755
1$
1&
#1760
0&
#1765
1%
1&
0)
#1770
0&
0'
0(
1)
#1775
0#
0$
1&
#1780
0&
#1785
0%
1&
0)
#1790
0&
1'
1)
#1795
1$
1&
#1800
0&
0'
1(
0)
#1805
1#
0$
1%
1&
1)
#1810
0&
1'
0(
0)
#1815
0#
1$
0%
1&
1)
#1820
0&
0'
0)
#1825
0$
1%
1&
1)
#1830
0&
1(
#1835
1#
0%
1&
0)
#1840
0&
1'
1)
#1845
1$
1&
#1850
0&
#1855
1%
1&
0)
#1860
0&
#1865
1&
#1870
0&
#1875
1&
#1880
0&
#1885
1&
#1890
0&
0'
1)
#1895
0$
1&
#1900
0&
0(
#1905
0#
0%
1&
0)
#1910
0&
#1915
1&
#1920
0&
#1925
1&
#1930
0&
1(
#1935
1#
1&
#1940
0&
1'
0(
1)
#1945
0#
1$
1&
#1950
0&
0'
0)
#1955
0$
1%
1&
1)
#1960
0&
1(
#1965
1#
0%
1&
0)
#1970
0&
1'
0(
1)
#1975
0#
1$
1&
#1980
0&
0'
1(
0)
#1985
1#
0$
1%
1&
1)
#1990
0&
1'
0(
0)
#1995
0#
1$
0%
1&
1)
#2000
0&
0'
0)
