tests/input/h11c/tb.sv
// H11c / D-028: SystemVerilog vector indexing, checked against Verilator.
// Each cycle the testbench drives random values and prints the selects that
// tests/vectorIndexTests.cc evaluates with HARM on the dumped trace (gen.sh).
module tb;
  logic clk = 0;
  logic [1:10] asc;     // ascending
  logic [10:3] off;     // descending, LSB index 3
  logic [7:0]  d;       // the usual form
  logic [0:0]  one;     // one bit, explicit range
  int unsigned cyc = 0;
  always #5 clk = ~clk;
  initial begin
    $dumpfile("ranges.vcd");
    $dumpvars(0, tb);
  end
  always @(negedge clk) begin
    asc <= 10'($urandom);
    off <= 8'($urandom);
    d   <= 8'($urandom);
    one <= 1'($urandom);
  end
  always @(posedge clk) begin
    // one line per cycle: the values HARM must compute, MSB first
    $display("CYC %0d asc[1]=%b asc[2]=%b asc[10]=%b asc[3:6]=%b asc[1:10]=%b off[3]=%b off[4]=%b off[10]=%b off[6:3]=%b off[10:7]=%b d[0]=%b d[7]=%b d[5:2]=%b one[0]=%b",
             cyc, asc[1], asc[2], asc[10], asc[3:6], asc[1:10], off[3], off[4], off[10], off[6:3], off[10:7], d[0], d[7], d[5:2], one[0]);
    cyc <= cyc + 1;
    if (cyc == 40) $finish;
  end
endmodule

tests/input/h11c/ranges.vcd
$version Generated by VerilatedVcd $end
$timescale 1ps $end
 $scope module $rootio $end
 $upscope $end
 $scope module tb $end
  $var wire 1 ' clk $end
  $var wire 10 # asc [1:10] $end
  $var wire 8 $ off [10:3] $end
  $var wire 8 % d [7:0] $end
  $var wire 1 & one [0:0] $end
  $var wire 32 ( cyc [31:0] $end
 $upscope $end
$enddefinitions $end


#0
b1111111111 #
b11111111 $
b00000010 %
1&
0'
b00000000000000000000000000000000 (
#5
1'
b00000000000000000000000000000001 (
#10
b0111111110 #
b00010100 $
b11111110 %
0'
#15
1'
b00000000000000000000000000000010 (
#20
b1010010000 #
b11110011 $
b01101011 %
0&
0'
#25
1'
b00000000000000000000000000000011 (
#30
b1011110111 #
b11010010 $
b11011011 %
0'
#35
1'
b00000000000000000000000000000100 (
#40
b0010000111 #
b10010001 $
b01010101 %
0'
#45
1'
b00000000000000000000000000000101 (
#50
b1011110010 #
b01010011 $
b00010001 %
1&
0'
#55
1'
b00000000000000000000000000000110 (
#60
b1001001001 #
b11110110 $
b10101110 %
0&
0'
#65
1'
b00000000000000000000000000000111 (
#70
b1010010101 #
b00010001 $
b01101100 %
1&
0'
#75
1'
b00000000000000000000000000001000 (
#80
b0100001010 #
b00111010 $
b00001000 %
0'
#85
1'
b00000000000000000000000000001001 (
#90
b1110001110 #
b10000100 $
b01001101 %
0&
0'
#95
1'
b00000000000000000000000000001010 (
#100
b1010100101 #
b10001110 $
b01001001 %
0'
#105
1'
b00000000000000000000000000001011 (
#110
b0001001000 #
b10110011 $
b10101000 %
0'
#115
1'
b00000000000000000000000000001100 (
#120
b0011001001 #
b01101100 $
b01011000 %
0'
#125
1'
b00000000000000000000000000001101 (
#130
b1011011111 #
b01111111 $
b10001000 %
1&
0'
#135
1'
b00000000000000000000000000001110 (
#140
b1110111001 #
b01111101 $
b00101010 %
0&
0'
#145
1'
b00000000000000000000000000001111 (
#150
b0001000000 #
b11010101 $
b01110101 %
1&
0'
#155
1'
b00000000000000000000000000010000 (
#160
b0000011001 #
b11100101 $
b01101100 %
0&
0'
#165
1'
b00000000000000000000000000010001 (
#170
b0010101001 #
b00010000 $
b10010101 %
0'
#175
1'
b00000000000000000000000000010010 (
#180
b1000011001 #
b01001100 $
b10011010 %
1&
0'
#185
1'
b00000000000000000000000000010011 (
#190
b0010000000 #
b00111010 $
b11110111 %
0&
0'
#195
1'
b00000000000000000000000000010100 (
#200
b0001010110 #
b10110010 $
b11001001 %
1&
0'
#205
1'
b00000000000000000000000000010101 (
#210
b1011111011 #
b01100011 $
b01001011 %
0&
0'
#215
1'
b00000000000000000000000000010110 (
#220
b1100000101 #
b10000101 $
b10111100 %
1&
0'
#225
1'
b00000000000000000000000000010111 (
#230
b0111110111 #
b00111110 $
b11001101 %
0&
0'
#235
1'
b00000000000000000000000000011000 (
#240
b0001110011 #
b00100101 $
b00111010 %
0'
#245
1'
b00000000000000000000000000011001 (
#250
b0011110111 #
b10001111 $
b10111001 %
1&
0'
#255
1'
b00000000000000000000000000011010 (
#260
b0110100101 #
b10011101 $
b11111011 %
0'
#265
1'
b00000000000000000000000000011011 (
#270
b0010111111 #
b00110110 $
b10011000 %
0&
0'
#275
1'
b00000000000000000000000000011100 (
#280
b1011101010 #
b10010101 $
b11000111 %
0'
#285
1'
b00000000000000000000000000011101 (
#290
b0010111011 #
b10000111 $
b11000001 %
1&
0'
#295
1'
b00000000000000000000000000011110 (
#300
b0101010001 #
b01001011 $
b01101101 %
0'
#305
1'
b00000000000000000000000000011111 (
#310
b0010100001 #
b01010110 $
b10111101 %
0'
#315
1'
b00000000000000000000000000100000 (
#320
b0101001110 #
b01000110 $
b11100010 %
0'
#325
1'
b00000000000000000000000000100001 (
#330
b1011100000 #
b00000011 $
b00000101 %
0&
0'
#335
1'
b00000000000000000000000000100010 (
#340
b1110001101 #
b11011111 $
b10100111 %
0'
#345
1'
b00000000000000000000000000100011 (
#350
b0110100011 #
b00010011 $
b01010110 %
1&
0'
#355
1'
b00000000000000000000000000100100 (
#360
b1001100111 #
b11001101 $
b11010001 %
0&
0'
#365
1'
b00000000000000000000000000100101 (
#370
b1010101100 #
b11000111 $
b11110001 %
0'
#375
1'
b00000000000000000000000000100110 (
#380
b0010100101 #
b00110101 $
b11000011 %
1&
0'
#385
1'
b00000000000000000000000000100111 (
#390
b1101110011 #
b10001011 $
b10011001 %
0'
#395
1'
b00000000000000000000000000101000 (
#400
b1010000001 #
b11101010 $
b10001110 %
0'
#405
1'
b00000000000000000000000000101001 (
