tests/input/coi/fsm/rtl/fsm.sv
// 3-state FSM with an enum state; outputs decoded from the state only
typedef enum logic [1:0] {
  IDLE = 2'd0,
  RUN  = 2'd1,
  DONE = 2'd2
} state_t;

module fsm (
    input  logic clk,
    input  logic rst,
    input  logic go,
    input  logic stop,
    output logic busy,
    output logic finished
);
  state_t state;
  always_ff @(posedge clk)
    if (rst) state <= IDLE;
    else
      case (state)
        IDLE: if (go) state <= RUN;
        RUN: if (stop) state <= DONE;
        DONE: state <= IDLE;
        default: state <= IDLE;
      endcase
  assign busy = (state == RUN);
  assign finished = (state == DONE);
endmodule

tests/input/coi/fsm/tb.sv
// testbench for the H4 COI fixture 'fsm': seeded random stimulus on the falling edge
`ifndef VCD
`define VCD "trace.vcd"
`endif
module tb;
  logic clk = 1'b0;
  logic rst;
  logic go;
  logic stop;
  logic busy;
  logic finished;
  fsm dut (.*);
  always #5 clk = ~clk;
`ifdef PERTURB
  `include "perturb.svh"
`endif
  initial begin
    string vcd;
    int unsigned seed;
    if (!$value$plusargs("vcd=%s", vcd)) vcd = `VCD;
    $dumpfile(vcd);
    $dumpvars(0, tb);
    if (!$value$plusargs("seed=%d", seed)) seed = 1;
    void'($urandom(seed));
    rst = '0; go = '0; stop = '0;
    rst = 1'b1;
    repeat (2) @(negedge clk);
    rst = 1'b0;
    repeat (200) begin
      @(negedge clk);
      rst = ($urandom % 40) == 0; go = ($urandom % 3) == 0; stop = ($urandom % 3) == 0;
    end
    $finish;
  end
endmodule

tests/input/coi/fsm/trace.vcd
$version Generated by VerilatedVcd $end
$timescale 1ps $end
 $scope module $rootio $end
 $upscope $end
 $scope module tb $end
  $var wire 1 & clk $end
  $var wire 1 ' rst $end
  $var wire 1 ( go $end
  $var wire 1 ) stop $end
  $var wire 1 # busy $end
  $var wire 1 $ finished $end
  $scope module dut $end
   $var wire 1 & clk $end
   $var wire 1 ' rst $end
   $var wire 1 ( go $end
   $var wire 1 ) stop $end
   $var wire 1 # busy $end
   $var wire 1 $ finished $end
   $var wire 2 % state [1:0] $end
  $upscope $end
  $scope module unnamedblk1 $end
   $var wire 32 * seed [31:0] $end
  $upscope $end
 $upscope $end
$enddefinitions $end


#0
0#
0$
b00 %
0&
1'
0(
0)
b00000000000000000000000000000001 *
#5
1&
#10
0&
#15
1&
#20
0&
0'
#25
1&
#30
0&
1(
#35
1#
b01 %
1&
#40
0&
#45
1&
#50
0&
#55
1&
#60
0&
0(
1)
#65
0#
1$
b10 %
1&
#70
0&
1(
#75
0$
b00 %
1&
#80
0&
0(
0)
#85
1&
#90
0&
#95
1&
#100
0&
1(
1)
#105
1#
b01 %
1&
#110
0&
0)
#115
1&
#120
0&
0(
#125
1&
#130
0&
#135
1&
#140
0&
#145
1&
#150
0&
#155
1&
#160
0&
#165
1&
#170
0&
1(
#175
1&
#180
0&
0(
1)
#185
0#
1$
b10 %
1&
#190
0&
#195
0$
b00 %
1&
#200
0&
1(
0)
#205
1#
b01 %
1&
#210
0&
#215
1&
#220
0&
0(
#225
1&
#230
0&
1)
#235
0#
1$
b10 %
1&
#240
0&
1(
0)
#245
0$
b00 %
1&
#250
0&
#255
1#
b01 %
1&
#260
0&
#265
1&
#270
0&
0(
1)
#275
0#
1$
b10 %
1&
#280
0&
0)
#285
0$
b00 %
1&
#290
0&
#295
1&
#300
0&
1(
#305
1#
b01 %
1&
#310
0&
#315
1&
#320
0&
0(
#325
1&
#330
0&
1)
#335
0#
1$
b10 %
1&
#340
0&
0)
#345
0$
b00 %
1&
#350
0&
1(
#355
1#
b01 %
1&
#360
0&
#365
1&
#370
0&
0(
1)
#375
0#
1$
b10 %
1&
#380
0&
0)
#385
0$
b00 %
1&
#390
0&
1)
#395
1&
#400
0&
1(
0)
#405
1#
b01 %
1&
#410
0&
1)
#415
0#
1$
b10 %
1&
#420
0&
0)
#425
0$
b00 %
1&
#430
0&
#435
1#
b01 %
1&
#440
0&
0(
#445
1&
#450
0&
1(
1)
#455
0#
1$
b10 %
1&
#460
0&
0)
#465
0$
b00 %
1&
#470
0&
0(
1)
#475
1&
#480
0&
1(
#485
1#
b01 %
1&
#490
0&
0)
#495
1&
#500
0&
0(
1)
#505
0#
1$
b10 %
1&
#510
0&
#515
0$
b00 %
1&
#520
0&
1(
0)
#525
1#
b01 %
1&
#530
0&
0(
#535
1&
#540
0&
1)
#545
0#
1$
b10 %
1&
#550
0&
#555
0$
b00 %
1&
#560
0&
1(
#565
1#
b01 %
1&
#570
0&
0(
0)
#575
1&
#580
0&
1(
#585
1&
#590
0&
0(
#595
1&
#600
0&
#605
1&
#610
0&
1)
#615
0#
1$
b10 %
1&
#620
0&
1(
0)
#625
0$
b00 %
1&
#630
0&
0(
#635
1&
#640
0&
1)
#645
1&
#650
0&
1(
#655
1#
b01 %
1&
#660
0&
0)
#665
1&
#670
0&
0(
1)
#675
0#
1$
b10 %
1&
#680
0&
1(
0)
#685
0$
b00 %
1&
#690
0&
0(
#695
1&
#700
0&
1(
#705
1#
b01 %
1&
#710
0&
0(
#715
1&
#720
0&
1)
#725
0#
1$
b10 %
1&
#730
0&
1(
0)
#735
0$
b00 %
1&
#740
0&
0(
1)
#745
1&
#750
0&
0)
#755
1&
#760
0&
1(
#765
1#
b01 %
1&
#770
0&
0(
#775
1&
#780
0&
1)
#785
0#
1$
b10 %
1&
#790
0&
1(
0)
#795
0$
b00 %
1&
#800
0&
0(
#805
1&
#810
0&
#815
1&
#820
0&
1)
#825
1&
#830
0&
0)
#835
1&
#840
0&
#845
1&
#850
0&
1)
#855
1&
#860
0&
0)
#865
1&
#870
0&
1)
#875
1&
#880
0&
1(
#885
1#
b01 %
1&
#890
0&
#895
0#
1$
b10 %
1&
#900
0&
0(
#905
0$
b00 %
1&
#910
0&
#915
1&
#920
0&
#925
1&
#930
0&
1(
#935
1#
b01 %
1&
#940
0&
0)
#945
1&
#950
0&
0(
#955
1&
#960
0&
1)
#965
0#
1$
b10 %
1&
#970
0&
1(
0)
#975
0$
b00 %
1&
#980
0&
1)
#985
1#
b01 %
1&
#990
0&
0(
#995
0#
1$
b10 %
1&
#1000
0&
1(
#1005
0$
b00 %
1&
#1010
0&
0(
0)
#1015
1&
#1020
0&
#1025
1&
#1030
0&
1)
#1035
1&
#1040
0&
0)
#1045
1&
#1050
0&
#1055
1&
#1060
0&
1(
#1065
1#
b01 %
1&
#1070
0&
0(
#1075
1&
#1080
0&
#1085
1&
#1090
0&
1(
#1095
1&
#1100
0&
1)
#1105
0#
1$
b10 %
1&
#1110
0&
0(
0)
#1115
0$
b00 %
1&
#1120
0&
1)
#1125
1&
#1130
0&
1(
0)
#1135
1#
b01 %
1&
#1140
0&
0(
#1145
1&
#1150
0&
#1155
1&
#1160
0&
#1165
1&
#1170
0&
#1175
1&
#1180
0&
1)
#1185
0#
1$
b10 %
1&
#1190
0&
0)
#1195
0$
b00 %
1&
#1200
0&
#1205
1&
#1210
0&
1)
#1215
1&
#1220
0&
1(
0)
#1225
1#
b01 %
1&
#1230
0&
0(
1)
#1235
0#
1$
b10 %
1&
#1240
0&
0)
#1245
0$
b00 %
1&
#1250
0&
#1255
1&
#1260
0&
#1265
1&
#1270
0&
1(
1)
#1275
1#
b01 %
1&
#1280
0&
0(
0)
#1285
1&
#1290
0&
#1295
1&
#1300
0&
1'
1)
#1305
0#
b00 %
1&
#1310
0&
0'
1(
0)
#1315
1#
b01 %
1&
#1320
0&
0(
#1325
1&
#1330
0&
#1335
1&
#1340
0&
1)
#1345
0#
1$
b10 %
1&
#1350
0&
0)
#1355
0$
b00 %
1&
#1360
0&
#1365
1&
#1370
0&
#1375
1&
#1380
0&
1(
1)
#1385
1#
b01 %
1&
#1390
0&
0(
0)
#1395
1&
#1400
0&
1'
1(
#1405
0#
b00 %
1&
#1410
0&
0'
#1415
1#
b01 %
1&
#1420
0&
0(
#1425
1&
#1430
0&
1(
#1435
1&
#1440
0&
1)
#1445
0#
1$
b10 %
1&
#1450
0&
0)
#1455
0$
b00 %
1&
#1460
0&
#1465
1#
b01 %
1&
#1470
0&
#1475
1&
#1480
0&
0(
#1485
1&
#1490
0&
1(
#1495
1&
#1500
0&
0(
1)
#1505
0#
1$
b10 %
1&
#1510
0&
0)
#1515
0$
b00 %
1&
#1520
0&
#1525
1&
#1530
0&
1(
#1535
1#
b01 %
1&
#1540
0&
1)
#1545
0#
1$
b10 %
1&
#1550
0&
0(
0)
#1555
0$
b00 %
1&
#1560
0&
1)
#1565
1&
#1570
0&
0)
#1575
1&
#1580
0&
#1585
1&
#1590
0&
#1595
1&
#1600
0&
#1605
1&
#1610
0&
#1615
1&
#1620
0&
1(
#1625
1#
b01 %
1&
#1630
0&
0(
#1635
1&
#1640
0&
#1645
1&
#1650
0&
#1655
1&
#1660
0&
1(
#1665
1&
#1670
0&
0(
#1675
1&
#1680
0&
1)
#1685
0#
1$
b10 %
1&
#1690
0&
0)
#1695
0$
b00 %
1&
#1700
0&
#1705
1&
#1710
0&
#1715
1&
#1720
0&
#1725
1&
#1730
0&
1)
#1735
1&
#1740
0&
0)
#1745
1&
#1750
0&
#1755
1&
#1760
0&
1(
#1765
1#
b01 %
1&
#1770
0&
0(
1)
#1775
0#
1$
b10 %
1&
#1780
0&
#1785
0$
b00 %
1&
#1790
0&
1(
0)
#1795
1#
b01 %
1&
#1800
0&
0(
#1805
1&
#1810
0&
1)
#1815
0#
1$
b10 %
1&
#1820
0&
#1825
0$
b00 %
1&
#1830
0&
1(
0)
#1835
1#
b01 %
1&
#1840
0&
0(
#1845
1&
#1850
0&
#1855
1&
#1860
0&
1)
#1865
0#
1$
b10 %
1&
#1870
0&
0)
#1875
0$
b00 %
1&
#1880
0&
1(
1)
#1885
1#
b01 %
1&
#1890
0&
0)
#1895
1&
#1900
0&
0(
#1905
1&
#1910
0&
#1915
1&
#1920
0&
#1925
1&
#1930
0&
1)
#1935
0#
1$
b10 %
1&
#1940
0&
1(
0)
#1945
0$
b00 %
1&
#1950
0&
#1955
1#
b01 %
1&
#1960
0&
0(
#1965
1&
#1970
0&
1(
1)
#1975
0#
1$
b10 %
1&
#1980
0&
0)
#1985
0$
b00 %
1&
#1990
0&
0(
#1995
1&
#2000
0&
1(
#2005
1#
b01 %
1&
#2010
0&
0(
1)
#2015
0#
1$
b10 %
1&
#2020
0&
1(
0)
