tests/input/stim.svh
// H11e (finding F-L7, D-029): the stimulus generator of the fixture testbenches.
// A simulator's $urandom sequence changes between versions (Verilator 5.031 -> 5.052), so the
// committed traces could not be reproduced. This xorshift32 generator (Marsaglia, 2003) is plain
// SystemVerilog: the same seed gives the same sequence on every simulator and version.
// Included inside the testbench module: `include "stim.svh"
int unsigned stim_state = 32'd1;

function automatic void stim_seed(int unsigned s);
  stim_state = (s == 0) ? 32'd1 : s; // xorshift must not start from 0
endfunction

function automatic int unsigned stim_next();
  stim_state ^= stim_state << 13;
  stim_state ^= stim_state >> 17;
  stim_state ^= stim_state << 5;
  return stim_state;
endfunction

tests/input/coi/arbiter/rtl/arbiter.sv
// 2-requester round-robin arbiter: grant from requests (combinational) and a priority register
module arbiter (
    input  logic       clk,
    input  logic       rst,
    input  logic [1:0] req,
    output logic [1:0] gnt
);
  logic prio;  // 1: requester 1 wins a conflict
  always_comb
    if (req == 2'b11) gnt = prio ? 2'b10 : 2'b01;
    else gnt = req;
  always_ff @(posedge clk)
    if (rst) prio <= 1'b0;
    else if (gnt[0]) prio <= 1'b1;
    else if (gnt[1]) prio <= 1'b0;
endmodule

tests/input/coi/arbiter/tb.sv
// testbench for the H4 COI fixture 'arbiter': seeded random stimulus on the falling edge
`ifndef VCD
`define VCD "trace.vcd"
`endif
module tb;
  `include "stim.svh"   // the stimulus generator (H11e, D-029)
  logic clk = 1'b0;
  logic rst;
  logic [1:0] req;
  logic [1:0] gnt;
  arbiter dut (.*);
  always #5 clk = ~clk;
`ifdef PERTURB
  `include "perturb.svh"
`endif
  initial begin
    string vcd;
    int unsigned seed;
    if (!$value$plusargs("vcd=%s", vcd)) vcd = `VCD;
    $dumpfile(vcd);
    $dumpvars(0, tb);
    if (!$value$plusargs("seed=%d", seed)) seed = 1;
    stim_seed(seed);
    rst = '0; req = '0;
    rst = 1'b1;
    repeat (2) @(negedge clk);
    rst = 1'b0;
    repeat (200) begin
      @(negedge clk);
      rst = (stim_next() % 40) == 0; req = 2'(stim_next());
    end
    $finish;
  end
endmodule

tests/input/coi/arbiter/trace.vcd
$version Generated by VerilatedVcd $end
$timescale 1ps $end
 $scope module $rootio $end
 $upscope $end
 $scope module tb $end
  $var wire 1 # clk $end
  $var wire 1 $ rst $end
  $var wire 2 % req [1:0] $end
  $var wire 2 & gnt [1:0] $end
  $scope module dut $end
   $var wire 1 # clk $end
   $var wire 1 $ rst $end
   $var wire 2 % req [1:0] $end
   $var wire 2 & gnt [1:0] $end
   $var wire 1 ' prio $end
  $upscope $end
  $scope module unnamedblk1 $end
   $var wire 32 ( seed [31:0] $end
  $upscope $end
 $upscope $end
$enddefinitions $end


#0
0#
1$
b00 %
b00 &
0'
b00000000000000000000000000000001 (
#5
1#
#10
0#
#15
1#
#20
0#
0$
#25
1#
#30
0#
b11 %
b01 &
#35
1#
b10 &
1'
#40
0#
b10 %
#45
1#
0'
#50
0#
b00 %
b00 &
#55
1#
#60
0#
#65
1#
#70
0#
b10 %
b10 &
#75
1#
#80
0#
b00 %
b00 &
#85
1#
#90
0#
b01 %
b01 &
#95
1#
1'
#100
0#
b11 %
b10 &
#105
1#
b01 &
0'
#110
0#
b01 %
#115
1#
1'
#120
0#
#125
1#
#130
0#
b11 %
b10 &
#135
1#
b01 &
0'
#140
0#
#145
1#
b10 &
1'
#150
0#
b00 %
b00 &
#155
1#
#160
0#
b10 %
b10 &
#165
1#
0'
#170
0#
#175
1#
#180
0#
b00 %
b00 &
#185
1#
#190
0#
#195
1#
#200
0#
b01 %
b01 &
#205
1#
1'
#210
0#
b10 %
b10 &
#215
1#
0'
#220
0#
b11 %
b01 &
#225
1#
b10 &
1'
#230
0#
b01 %
b01 &
#235
1#
#240
0#
#245
1#
#250
0#
#255
1#
#260
0#
b10 %
b10 &
#265
1#
0'
#270
0#
b00 %
b00 &
#275
1#
#280
0#
b10 %
b10 &
#285
1#
#290
0#
b00 %
b00 &
#295
1#
#300
0#
#305
1#
#310
0#
#315
1#
#320
0#
#325
1#
#330
0#
b01 %
b01 &
#335
1#
1'
#340
0#
b10 %
b10 &
#345
1#
0'
#350
0#
#355
1#
#360
0#
b00 %
b00 &
#365
1#
#370
0#
b11 %
b01 &
#375
1#
b10 &
1'
#380
0#
b01 %
b01 &
#385
1#
#390
0#
b11 %
b10 &
#395
1#
b01 &
0'
#400
0#
#405
1#
b10 &
1'
#410
0#
b00 %
b00 &
#415
1#
#420
0#
b10 %
b10 &
#425
1#
0'
#430
0#
b00 %
b00 &
#435
1#
#440
0#
#445
1#
#450
0#
#455
1#
#460
0#
b11 %
b01 &
#465
1#
b10 &
1'
#470
0#
#475
1#
b01 &
0'
#480
0#
#485
1#
b10 &
1'
#490
0#
b01 %
b01 &
#495
1#
#500
0#
b00 %
b00 &
#505
1#
#510
0#
b10 %
b10 &
#515
1#
0'
#520
0#
b00 %
b00 &
#525
1#
#530
0#
b10 %
b10 &
#535
1#
#540
0#
#545
1#
#550
0#
b11 %
b01 &
#555
1#
b10 &
1'
#560
0#
b01 %
b01 &
#565
1#
#570
0#
b00 %
b00 &
#575
1#
#580
0#
b11 %
b10 &
#585
1#
b01 &
0'
#590
0#
#595
1#
b10 &
1'
#600
0#
b00 %
b00 &
#605
1#
#610
0#
b11 %
b10 &
#615
1#
b01 &
0'
#620
0#
#625
1#
b10 &
1'
#630
0#
#635
1#
b01 &
0'
#640
0#
b01 %
#645
1#
1'
#650
0#
b00 %
b00 &
#655
1#
#660
0#
b11 %
b10 &
#665
1#
b01 &
0'
#670
0#
b10 %
b10 &
#675
1#
#680
0#
b11 %
b01 &
#685
1#
b10 &
1'
#690
0#
b01 %
b01 &
#695
1#
#700
0#
b11 %
b10 &
#705
1#
b01 &
0'
#710
0#
#715
1#
b10 &
1'
#720
0#
b00 %
b00 &
#725
1#
#730
0#
b01 %
b01 &
#735
1#
#740
0#
b00 %
b00 &
#745
1#
#750
0#
b01 %
b01 &
#755
1#
#760
0#
b00 %
b00 &
#765
1#
#770
0#
b11 %
b10 &
#775
1#
b01 &
0'
#780
0#
b10 %
b10 &
#785
1#
#790
0#
#795
1#
#800
0#
#805
1#
#810
0#
b11 %
b01 &
#815
1#
b10 &
1'
#820
0#
#825
1#
b01 &
0'
#830
0#
#835
1#
b10 &
1'
#840
0#
b00 %
b00 &
#845
1#
#850
0#
b01 %
b01 &
#855
1#
#860
0#
b10 %
b10 &
#865
1#
0'
#870
0#
b11 %
b01 &
#875
1#
b10 &
1'
#880
0#
b01 %
b01 &
#885
1#
#890
0#
b00 %
b00 &
#895
1#
#900
0#
#905
1#
#910
0#
#915
1#
#920
0#
b10 %
b10 &
#925
1#
0'
#930
0#
b00 %
b00 &
#935
1#
#940
0#
b11 %
b01 &
#945
1#
b10 &
1'
#950
0#
b01 %
b01 &
#955
1#
#960
0#
b10 %
b10 &
#965
1#
0'
#970
0#
b01 %
b01 &
#975
1#
1'
#980
0#
b00 %
b00 &
#985
1#
#990
0#
b11 %
b10 &
#995
1#
b01 &
0'
#1000
0#
b10 %
b10 &
#1005
1#
#1010
0#
b11 %
b01 &
#1015
1#
b10 &
1'
#1020
0#
#1025
1#
b01 &
0'
#1030
0#
#1035
1#
b10 &
1'
#1040
0#
#1045
1#
b01 &
0'
#1050
0#
b00 %
b00 &
#1055
1#
#1060
0#
b11 %
b01 &
#1065
1#
b10 &
1'
#1070
0#
b10 %
#1075
1#
0'
#1080
0#
#1085
1#
#1090
0#
#1095
1#
#1100
0#
b11 %
b01 &
#1105
1#
b10 &
1'
#1110
0#
#1115
1#
b01 &
0'
#1120
0#
#1125
1#
b10 &
1'
#1130
0#
b00 %
b00 &
#1135
1#
#1140
0#
b10 %
b10 &
#1145
1#
0'
#1150
0#
b11 %
b01 &
#1155
1#
b10 &
1'
#1160
0#
#1165
1#
b01 &
0'
#1170
0#
#1175
1#
b10 &
1'
#1180
0#
b01 %
b01 &
#1185
1#
#1190
0#
b11 %
b10 &
#1195
1#
b01 &
0'
#1200
0#
b01 %
#1205
1#
1'
#1210
0#
#1215
1#
#1220
0#
#1225
1#
#1230
0#
b11 %
b10 &
#1235
1#
b01 &
0'
#1240
0#
b01 %
#1245
1#
1'
#1250
0#
#1255
1#
#1260
0#
b11 %
b10 &
#1265
1#
b01 &
0'
#1270
0#
b10 %
b10 &
#1275
1#
#1280
0#
#1285
1#
#1290
0#
#1295
1#
#1300
0#
b01 %
b01 &
#1305
1#
1'
#1310
0#
b00 %
b00 &
#1315
1#
#1320
0#
#1325
1#
#1330
0#
b11 %
b10 &
#1335
1#
b01 &
0'
#1340
0#
b01 %
#1345
1#
1'
#1350
0#
#1355
1#
#1360
0#
b11 %
b10 &
#1365
1#
b01 &
0'
#1370
0#
b00 %
b00 &
#1375
1#
#1380
0#
b11 %
b01 &
#1385
1#
b10 &
1'
#1390
0#
b01 %
b01 &
#1395
1#
#1400
0#
b10 %
b10 &
#1405
1#
0'
#1410
0#
b01 %
b01 &
#1415
1#
1'
#1420
0#
#1425
1#
#1430
0#
b11 %
b10 &
#1435
1#
b01 &
0'
#1440
0#
b00 %
b00 &
#1445
1#
#1450
0#
#1455
1#
#1460
0#
b10 %
b10 &
#1465
1#
#1470
0#
b11 %
b01 &
#1475
1#
b10 &
1'
#1480
0#
b10 %
#1485
1#
0'
#1490
0#
b00 %
b00 &
#1495
1#
#1500
0#
b01 %
b01 &
#1505
1#
1'
#1510
0#
b11 %
b10 &
#1515
1#
b01 &
0'
#1520
0#
b01 %
#1525
1#
1'
#1530
0#
b00 %
b00 &
#1535
1#
#1540
0#
b01 %
b01 &
#1545
1#
#1550
0#
b11 %
b10 &
#1555
1#
b01 &
0'
#1560
0#
b10 %
b10 &
#1565
1#
#1570
0#
#1575
1#
#1580
0#
b01 %
b01 &
#1585
1#
1'
#1590
0#
b00 %
b00 &
#1595
1#
#1600
0#
b11 %
b10 &
#1605
1#
b01 &
0'
#1610
0#
b00 %
b00 &
#1615
1#
#1620
0#
b11 %
b01 &
#1625
1#
b10 &
1'
#1630
0#
b01 %
b01 &
#1635
1#
#1640
0#
b11 %
b10 &
#1645
1#
b01 &
0'
#1650
0#
#1655
1#
b10 &
1'
#1660
0#
b01 %
b01 &
#1665
1#
#1670
0#
b00 %
b00 &
#1675
1#
#1680
0#
#1685
1#
#1690
0#
b10 %
b10 &
#1695
1#
0'
#1700
0#
b11 %
b01 &
#1705
1#
b10 &
1'
#1710
0#
b00 %
b00 &
#1715
1#
#1720
0#
b01 %
b01 &
#1725
1#
#1730
0#
b10 %
b10 &
#1735
1#
0'
#1740
0#
#1745
1#
#1750
0#
b00 %
b00 &
#1755
1#
#1760
0#
b11 %
b01 &
#1765
1#
b10 &
1'
#1770
0#
b01 %
b01 &
#1775
1#
#1780
0#
#1785
1#
#1790
0#
b10 %
b10 &
#1795
1#
0'
#1800
0#
b00 %
b00 &
#1805
1#
#1810
0#
b10 %
b10 &
#1815
1#
#1820
0#
b11 %
b01 &
#1825
1#
b10 &
1'
#1830
0#
b10 %
#1835
1#
0'
#1840
0#
#1845
1#
#1850
0#
b01 %
b01 &
#1855
1#
1'
#1860
0#
b11 %
b10 &
#1865
1#
b01 &
0'
#1870
0#
b01 %
#1875
1#
1'
#1880
0#
#1885
1#
#1890
0#
#1895
1#
#1900
0#
b11 %
b10 &
#1905
1#
b01 &
0'
#1910
0#
b01 %
#1915
1#
1'
#1920
0#
b10 %
b10 &
#1925
1#
0'
#1930
0#
b00 %
b00 &
#1935
1#
#1940
0#
b10 %
b10 &
#1945
1#
#1950
0#
b11 %
b01 &
#1955
1#
b10 &
1'
#1960
0#
b00 %
b00 &
#1965
1#
#1970
0#
#1975
1#
#1980
0#
b11 %
b10 &
#1985
1#
b01 &
0'
#1990
0#
b00 %
b00 &
#1995
1#
#2000
0#
b01 %
b01 &
#2005
1#
1'
#2010
0#
b00 %
b00 &
#2015
1#
#2020
0#
b10 %
b10 &
